fcgr_py/__init__.py
fcgr_py/alignment.py
fcgr_py/fcgr_pipeline.py
fcgr_py/get_refs.py
fcgr_py/postprocessing.py
fcgr_py/preprocessing-Copy1.py
fcgr_py/preprocessing.py
fcgr_py/process.py
fcgr_py/variation.py
fcgr_py-0.1.2.dist-info/METADATA
fcgr_py-0.1.2.dist-info/WHEEL
fcgr_py-0.1.2.dist-info/top_level.txt
fcgr_py-0.1.2.dist-info/RECORD
