Metadata-Version: 2.1
Name: fcgr-py
Version: 0.1.2
Summary: FCGR Pipeline
Home-page: UNKNOWN
Author: Madison Berry
Author-email: madison.berry@duke.edu
License: MIT
Platform: UNKNOWN
